Workbook
Name Slicer_Category: #N/A
Name Slicer_Months__Date: #N/A
Name Slicer_Region: #N/A
Name Slicer_Years__Date: #N/A

Sheet Project Instructions
A1: PR. Final Project - "Data Intelligence Dashboard"
A2: Dataset: Use the 'Final Project Dataset' sheet containing 200+ records of customer transactions. Objective: Create a full-fledged analysis and reporting solution using Excel to analyze customer transactions, find insights, and build visualizations and dashboards. Key Topics to Implement: - Date & Time Functions: TODAY, NOW, DATEDIF, EOMONTH - FILTER Function for multi-value returns - Conditional Formatting with Icons/Arrows - Create Timestamp (using NOW and iterative calculations) - WHAT-IF Analysis: Scenario Manager, Goal Seek - Linear Regression using Data Analysis Toolpak - Data Analysis & Storytelling from the dataset - Use GroupBy concepts to find High-Value Customers using formulas - Create Dashboard using: - Pivot Tables - Pivot Charts (Bar, Line, Pie) - Slicers and Timelines - KPI Indicators with Conditional Formatting - Find most frequently purchased product or repeating names using formulas - Compare two lists and extract matching names in a new column - Create Abbreviations using TEXT functions - Build a final report with insights and storytelling Deliverable: - Well-structured workbook with multiple sheets (Raw Data, Analysis, Visualizations, Dashboard) - Summary Insights with key metrics: Total Revenue, Top Customers, Most Sold Products, Regional Sales - Use of all required formulas and functions as listed above

Sheet Final Project Dataset
A1: Transaction_ID | B1: Date | C1: Customer_ID | D1: Customer_Name | E1: Product_ID | F1: Product_Name | G1: Category | H1: Quantity | I1: Unit_Price | J1: Payment_Method | K1: Region | L1: Customer_Segment | M1: Customer_Since | N1: Total_Amount | O1: Date_Different | P1: Time Stamp | Q1: Total Revenue | R1: Most Frequently Purchased Product | S1: Abbreviations
A2: TRX0155 | B2: 45393 | C2: CUST023 | D2: Paul Baker | E2: P009 | F2: Monitor | G2: Electronics | H2: 3 | I2: 249.99 | J2: Cash | K2: Central | L2: Basic | M2: 44425 | N2: 749.97 | O2: {=DATEDIF(M2:M251,B2:B251,"Y")} -> 2 | P2: =IF(A2<>"", IF(P2="", NOW(), P2), "") -> 46105.94 | Q2: =SUMIFS(N:N, C:C, C2) -> 8309.74 | R2: =COUNTIF($F:$F,F2) -> 26 | S2: =LEFT(D2,1) & MID(D2,FIND(" ",D2)+1,1) -> PB | V2: 1. Date & Time Functions: TODAY, NOW, DATEDIF, EOMONTH
A3: TRX0023 | B3: 45396 | C3: CUST013 | D3: Joseph Jackson | E3: P009 | F3: Monitor | G3: Electronics | H3: 3 | I3: 249.99 | J3: Credit Card | K3: Central | L3: Premium | M3: 44575 | N3: 749.97 | O3: 2 | P3: =IF(A3<>"", IF(P3="", NOW(), P3), "") -> 46105.94 | Q3: =SUMIFS(N:N, C:C, C3) -> 6949.84 | R3: =COUNTIF($F:$F,F3) -> 26 | S3: =LEFT(D3,1) & MID(D3,FIND(" ",D3)+1,1) -> JJ | V3: Today | W3: Now | X3: EOMONTH
A4: TRX0139 | B4: 45399 | C4: CUST021 | D4: Kevin Scott | E4: P005 | F4: Blender | G4: Appliances | H4: 3 | I4: 59.99 | J4: PayPal | K4: South | L4: Standard | M4: 45262 | N4: 179.97 | O4: 0 | P4: =IF(A4<>"", IF(P4="", NOW(), P4), "") -> 46105.94 | Q4: =SUMIFS(N:N, C:C, C4) -> 3259.87 | R4: =COUNTIF($F:$F,F4) -> 29 | S4: =LEFT(D4,1) & MID(D4,FIND(" ",D4)+1,1) -> KS | V4: =TODAY() -> 46107 | W4: =NOW() -> 46107.77 | X4: =EOMONTH(M2,0) -> 44439
A5: TRX0043 | B5: 45400 | C5: CUST046 | D5: Kathleen Bennett | E5: P005 | F5: Blender | G5: Appliances | H5: 3 | I5: 59.99 | J5: Cash | K5: North | L5: Premium | M5: 45114 | N5: 179.97 | O5: 0 | P5: =IF(A5<>"", IF(P5="", NOW(), P5), "") -> 46105.94 | Q5: =SUMIFS(N:N, C:C, C5) -> 4309.81 | R5: =COUNTIF($F:$F,F5) -> 29 | S5: =LEFT(D5,1) & MID(D5,FIND(" ",D5)+1,1) -> KB
A6: TRX0212 | B6: 45400 | C6: CUST003 | D6: Michael Brown | E6: P008 | F6: Bookshelf | G6: Furniture | H6: 5 | I6: 149.99 | J6: Credit Card | K6: North | L6: Premium | M6: 45295 | N6: 749.95 | O6: 0 | P6: =IF(A6<>"", IF(P6="", NOW(), P6), "") -> 46105.94 | Q6: =SUMIFS(N:N, C:C, C6) -> 6169.74 | R6: =COUNTIF($F:$F,F6) -> 35 | S6: =LEFT(D6,1) & MID(D6,FIND(" ",D6)+1,1) -> MB | V6: 2. FILTER Function for multi-value returns
A7: TRX0092 | B7: 45403 | C7: CUST024 | D7: Dorothy Nelson | E7: P005 | F7: Blender | G7: Appliances | H7: 2 | I7: 59.99 | J7: Cash | K7: West | L7: Standard | M7: 44746 | N7: 119.98 | O7: 1 | P7: =IF(A7<>"", IF(P7="", NOW(), P7), "") -> 46105.94 | Q7: =SUMIFS(N:N, C:C, C7) -> 8269.79 | R7: =COUNTIF($F:$F,F7) -> 29 | S7: =LEFT(D7,1) & MID(D7,FIND(" ",D7)+1,1) -> DN | V7: Show only Electronics + West Region
A8: TRX0193 | B8: 45403 | C8: CUST024 | D8: Dorothy Nelson | E8: P003 | F8: Headphones | G8: Electronics | H8: 5 | I8: 149.99 | J8: Credit Card | K8: Central | L8: Standard | M8: 44418 | N8: 749.95 | O8: 2 | P8: =IF(A8<>"", IF(P8="", NOW(), P8), "") -> 46105.94 | Q8: =SUMIFS(N:N, C:C, C8) -> 8269.79 | R8: =COUNTIF($F:$F,F8) -> 16 | S8: =LEFT(D8,1) & MID(D8,FIND(" ",D8)+1,1) -> DN | V8: {=_xlfn._xlws.FILTER(A2:L251,(F2:F251="Laptop")*(K2:K251="West"))} -> TRX0122 | W8: 45410 | X8: CUST025 | Y8: Mark Carter | Z8: P001 | AA8: Laptop | AB8: Electronics | AC8: 4 | AD8: 899.99 | AE8: Credit Card | AF8: West | AG8: Standard
A9: TRX0240 | B9: 45403 | C9: CUST017 | D9: Charles Allen | E9: P005 | F9: Blender | G9: Appliances | H9: 3 | I9: 59.99 | J9: Debit Card | K9: South | L9: Basic | M9: 45007 | N9: 179.97 | O9: 1 | P9: =IF(A9<>"", IF(P9="", NOW(), P9), "") -> 46105.94 | Q9: =SUMIFS(N:N, C:C, C9) -> 5089.73 | R9: =COUNTIF($F:$F,F9) -> 29 | S9: =LEFT(D9,1) & MID(D9,FIND(" ",D9)+1,1) -> CA | V9: TRX0041 | W9: 45432 | X9: CUST021 | Y9: Kevin Scott | Z9: P001 | AA9: Laptop | AB9: Electronics | AC9: 1 | AD9: 899.99 | AE9: Credit Card | AF9: West | AG9: Premium
A10: TRX0135 | B10: 45405 | C10: CUST009 | D10: Robert Thomas | E10: P001 | F10: Laptop | G10: Electronics | H10: 3 | I10: 899.99 | J10: PayPal | K10: East | L10: Standard | M10: 45299 | N10: 2699.97 | O10: 0 | P10: =IF(A10<>"", IF(P10="", NOW(), P10), "") -> 46105.94 | Q10: =SUMIFS(N:N, C:C, C10) -> 3509.9 | R10: =COUNTIF($F:$F,F10) -> 24 | S10: =LEFT(D10,1) & MID(D10,FIND(" ",D10)+1,1) -> RT | V10: TRX0158 | W10: 45579 | X10: CUST027 | Y10: George Adams | Z10: P001 | AA10: Laptop | AB10: Electronics | AC10: 3 | AD10: 899.99 | AE10: PayPal | AF10: West | AG10: Basic
A11: TRX0185 | B11: 45408 | C11: CUST026 | D11: Karen Hill | E11: P005 | F11: Blender | G11: Appliances | H11: 3 | I11: 59.99 | J11: Cash | K11: West | L11: Premium | M11: 45207 | N11: 179.97 | O11: 0 | P11: =IF(A11<>"", IF(P11="", NOW(), P11), "") -> 46105.94 | Q11: =SUMIFS(N:N, C:C, C11) -> 8009.77 | R11: =COUNTIF($F:$F,F11) -> 29 | S11: =LEFT(D11,1) & MID(D11,FIND(" ",D11)+1,1) -> KH
A12: TRX0138 | B12: 45408 | C12: CUST022 | D12: Susan Green | E12: P008 | F12: Bookshelf | G12: Furniture | H12: 1 | I12: 149.99 | J12: Credit Card | K12: West | L12: Standard | M12: 45103 | N12: 149.99 | O12: 0 | P12: =IF(A12<>"", IF(P12="", NOW(), P12), "") -> 46105.94 | Q12: =SUMIFS(N:N, C:C, C12) -> 1979.89 | R12: =COUNTIF($F:$F,F12) -> 35 | S12: =LEFT(D12,1) & MID(D12,FIND(" ",D12)+1,1) -> SG | V12: 4.Conditional Formatting with Icons/Arrows
A13: TRX0209 | B13: 45408 | C13: CUST046 | D13: Kathleen Bennett | E13: P008 | F13: Bookshelf | G13: Furniture | H13: 5 | I13: 149.99 | J13: Debit Card | K13: North | L13: Basic | M13: 44830 | N13: 749.95 | O13: 1 | P13: =IF(A13<>"", IF(P13="", NOW(), P13), "") -> 46105.94 | Q13: =SUMIFS(N:N, C:C, C13) -> 4309.81 | R13: =COUNTIF($F:$F,F13) -> 35 | S13: =LEFT(D13,1) & MID(D13,FIND(" ",D13)+1,1) -> KB | V13: year | W13: Month | X13: Toatl_amount | Y13: Sales_Growth
A14: TRX0246 | B14: 45408 | C14: CUST041 | D14: Peter Richardson | E14: P008 | F14: Bookshelf | G14: Furniture | H14: 3 | I14: 149.99 | J14: Cash | K14: North | L14: Premium | M14: 44806 | N14: 449.97 | O14: 1 | P14: =IF(A14<>"", IF(P14="", NOW(), P14), "") -> 46105.94 | Q14: =SUMIFS(N:N, C:C, C14) -> 5949.85 | R14: =COUNTIF($F:$F,F14) -> 35 | S14: =LEFT(D14,1) & MID(D14,FIND(" ",D14)+1,1) -> PR | V14: 2024 | W14: Apr | X14: 20919.33 | Y14: -
A15: TRX0067 | B15: 45409 | C15: CUST043 | D15: Dennis Gray | E15: P005 | F15: Blender | G15: Appliances | H15: 3 | I15: 59.99 | J15: Credit Card | K15: North | L15: Standard | M15: 45351 | N15: 179.97 | O15: 0 | P15: =IF(A15<>"", IF(P15="", NOW(), P15), "") -> 46105.94 | Q15: =SUMIFS(N:N, C:C, C15) -> 479.92 | R15: =COUNTIF($F:$F,F15) -> 29 | S15: =LEFT(D15,1) & MID(D15,FIND(" ",D15)+1,1) -> DG | W15: May | X15: 17039.35 | Y15: =(X15-X14)/X14 -> -0.18547344
A16: TRX0191 | B16: 45409 | C16: CUST038 | D16: Michelle Rogers | E16: P002 | F16: Smartphone | G16: Electronics | H16: 3 | I16: 699.99 | J16: Credit Card | K16: West | L16: Basic | M16: 44577 | N16: 2099.97 | O16: 2 | P16: =IF(A16<>"", IF(P16="", NOW(), P16), "") -> 46105.94 | Q16: =SUMIFS(N:N, C:C, C16) -> 4199.94 | R16: =COUNTIF($F:$F,F16) -> 31 | S16: =LEFT(D16,1) & MID(D16,FIND(" ",D16)+1,1) -> MR | W16: Jun | X16: 19299.45 | Y16: =(X16-X15)/X15 -> 0.13264004
A17: TRX0230 | B17: 45409 | C17: CUST027 | D17: George Adams | E17: P001 | F17: Laptop | G17: Electronics | H17: 1 | I17: 899.99 | J17: Debit Card | K17: North | L17: Standard | M17: 44920 | N17: 899.99 | O17: 1 | P17: =IF(A17<>"", IF(P17="", NOW(), P17), "") -> 46105.94 | Q17: =SUMIFS(N:N, C:C, C17) -> 3779.93 | R17: =COUNTIF($F:$F,F17) -> 24 | S17: =LEFT(D17,1) & MID(D17,FIND(" ",D17)+1,1) -> GA | W17: Jul | X17: 18479.4 | Y17: =(X17-X16)/X16 -> -0.042490848
A18: TRX0049 | B18: 45410 | C18: CUST025 | D18: Mark Carter | E18: P008 | F18: Bookshelf | G18: Furniture | H18: 4 | I18: 149.99 | J18: Debit Card | K18: North | L18: Premium | M18: 45374 | N18: 599.96 | O18: 0 | P18: =IF(A18<>"", IF(P18="", NOW(), P18), "") -> 46105.94 | Q18: =SUMIFS(N:N, C:C, C18) -> 15659.65 | R18: =COUNTIF($F:$F,F18) -> 35 | S18: =LEFT(D18,1) & MID(D18,FIND(" ",D18)+1,1) -> MC | W18: Aug | X18: 15759.43 | Y18: =(X18-X17)/X17 -> -0.1471893
A19: TRX0134 | B19: 45410 | C19: CUST010 | D19: Maria Garcia | E19: P002 | F19: Smartphone | G19: Electronics | H19: 2 | I19: 699.99 | J19: Cash | K19: North | L19: Basic | M19: 44781 | N19: 1399.98 | O19: 1 | P19: =IF(A19<>"", IF(P19="", NOW(), P19), "") -> 46105.94 | Q19: =SUMIFS(N:N, C:C, C19) -> 1909.93 | R19: =COUNTIF($F:$F,F19) -> 31 | S19: =LEFT(D19,1) & MID(D19,FIND(" ",D19)+1,1) -> MG | W19: Sep | X19: 12989.51 | Y19: =(X19-X18)/X18 -> -0.1757627
A20: TRX0122 | B20: 45410 | C20: CUST025 | D20: Mark Carter | E20: P001 | F20: Laptop | G20: Electronics | H20: 4 | I20: 899.99 | J20: Credit Card | K20: West | L20: Standard | M20: 45327 | N20: 3599.96 | O20: 0 | P20: =IF(A20<>"", IF(P20="", NOW(), P20), "") -> 46105.94 | Q20: =SUMIFS(N:N, C:C, C20) -> 15659.65 | R20: =COUNTIF($F:$F,F20) -> 24 | S20: =LEFT(D20,1) & MID(D20,FIND(" ",D20)+1,1) -> MC | W20: Oct | X20: 20609.52 | Y20: =(X20-X19)/X19 -> 0.58662798
A21: TRX0222 | B21: 45410 | C21: CUST048 | D21: Virginia Sanders | E21: P009 | F21: Monitor | G21: Electronics | H21: 3 | I21: 249.99 | J21: Credit Card | K21: North | L21: Premium | M21: 45224 | N21: 749.97 | O21: 0 | P21: =IF(A21<>"", IF(P21="", NOW(), P21), "") -> 46105.94 | Q21: =SUMIFS(N:N, C:C, C21) -> 4789.79 | R21: =COUNTIF($F:$F,F21) -> 26 | S21: =LEFT(D21,1) & MID(D21,FIND(" ",D21)+1,1) -> VS | W21: Nov | X21: 12309.44 | Y21: =(X21-X20)/X20 -> -0.40273039
A22: TRX0231 | B22: 45412 | C22: CUST018 | D22: Barbara Young | E22: P002 | F22: Smartphone | G22: Electronics | H22: 5 | I22: 699.99 | J22: Cash | K22: West | L22: Basic | M22: 45167 | N22: 3499.95 | O22: 0 | P22: =IF(A22<>"", IF(P22="", NOW(), P22), "") -> 46105.94 | Q22: =SUMIFS(N:N, C:C, C22) -> 10649.8 | R22: =COUNTIF($F:$F,F22) -> 31 | S22: =LEFT(D22,1) & MID(D22,FIND(" ",D22)+1,1) -> BY | W22: Dec | X22: 23039.3 | Y22: =(X22-X21)/X21 -> 0.87167735
A23: TRX0239 | B23: 45413 | C23: CUST012 | D23: Patricia Moore | E23: P002 | F23: Smartphone | G23: Electronics | H23: 4 | I23: 699.99 | J23: Cash | K23: East | L23: Standard | M23: 44409 | N23: 2799.96 | O23: 2 | P23: =IF(A23<>"", IF(P23="", NOW(), P23), "") -> 46105.94 | Q23: =SUMIFS(N:N, C:C, C23) -> 9799.73 | R23: =COUNTIF($F:$F,F23) -> 31 | S23: =LEFT(D23,1) & MID(D23,FIND(" ",D23)+1,1) -> PM | V23: 2025 | W23: Jan | X23: 25799.15 | Y23: =(X23-X22)/X22 -> 0.1197888
A24: TRX0204 | B24: 45415 | C24: CUST044 | D24: Cynthia Price | E24: P009 | F24: Monitor | G24: Electronics | H24: 4 | I24: 249.99 | J24: PayPal | K24: North | L24: Standard | M24: 44468 | N24: 999.96 | O24: 2 | P24: =IF(A24<>"", IF(P24="", NOW(), P24), "") -> 46105.94 | Q24: =SUMIFS(N:N, C:C, C24) -> 3769.83 | R24: =COUNTIF($F:$F,F24) -> 26 | S24: =LEFT(D24,1) & MID(D24,FIND(" ",D24)+1,1) -> CP | W24: Feb | X24: 16069.38 | Y24: =(X24-X23)/X23 -> -0.37713529
A25: TRX0242 | B25: 45416 | C25: CUST025 | D25: Mark Carter | E25: P007 | F25: Desk | G25: Furniture | H25: 4 | I25: 299.99 | J25: Cash | K25: West | L25: Premium | M25: 44716 | N25: 1199.96 | O25: 1 | P25: =IF(A25<>"", IF(P25="", NOW(), P25), "") -> 46105.94 | Q25: =SUMIFS(N:N, C:C, C25) -> 15659.65 | R25: =COUNTIF($F:$F,F25) -> 26 | S25: =LEFT(D25,1) & MID(D25,FIND(" ",D25)+1,1) -> MC | W25: Mar | X25: 19899.38 | Y25: =(X25-X24)/X24 -> 0.23834149
A26: TRX0071 | B26: 45422 | C26: CUST036 | D26: Nancy Collins | E26: P009 | F26: Monitor | G26: Electronics | H26: 5 | I26: 249.99 | J26: Credit Card | K26: West | L26: Standard | M26: 44525 | N26: 1249.95 | O26: 2 | P26: =IF(A26<>"", IF(P26="", NOW(), P26), "") -> 46105.94 | Q26: =SUMIFS(N:N, C:C, C26) -> 4189.77 | R26: =COUNTIF($F:$F,F26) -> 26 | S26: =LEFT(D26,1) & MID(D26,FIND(" ",D26)+1,1) -> NC | W26: Apr | X26: 6979.83 | Y26: =(X26-X25)/X25 -> -0.64924385
A27: TRX0040 | B27: 45424 | C27: CUST022 | D27: Susan Green | E27: P007 | F27: Desk | G27: Furniture | H27: 5 | I27: 299.99 | J27: PayPal | K27: East | L27: Basic | M27: 45168 | N27: 1499.95 | O27: 0 | P27: =IF(A27<>"", IF(P27="", NOW(), P27), "") -> 46105.94 | Q27: =SUMIFS(N:N, C:C, C27) -> 1979.89 | R27: =COUNTIF($F:$F,F27) -> 26 | S27: =LEFT(D27,1) & MID(D27,FIND(" ",D27)+1,1) -> SG
A28: TRX0235 | B28: 45424 | C28: CUST014 | D28: Linda Martin | E28: P004 | F28: Coffee Maker | G28: Appliances | H28: 3 | I28: 79.99 | J28: PayPal | K28: East | L28: Premium | M28: 45012 | N28: 239.97 | O28: 1 | P28: =IF(A28<>"", IF(P28="", NOW(), P28), "") -> 46105.94 | Q28: =SUMIFS(N:N, C:C, C28) -> 1289.9 | R28: =COUNTIF($F:$F,F28) -> 14 | S28: =LEFT(D28,1) & MID(D28,FIND(" ",D28)+1,1) -> LM
A29: TRX0004 | B29: 45424 | C29: CUST012 | D29: Patricia Moore | E29: P010 | F29: Keyboard | G29: Electronics | H29: 5 | I29: 89.99 | J29: Cash | K29: North | L29: Premium | M29: 44919 | N29: 449.95 | O29: 1 | P29: =IF(A29<>"", IF(P29="", NOW(), P29), "") -> 46105.94 | Q29: =SUMIFS(N:N, C:C, C29) -> 9799.73 | R29: =COUNTIF($F:$F,F29) -> 34 | S29: =LEFT(D29,1) & MID(D29,FIND(" ",D29)+1,1) -> PM | V29: 5.WHAT-IF Analysis: Scenario Manager, Goal Seek | AB29: =SUM(I2:I251) -> 74167.5 | AC29: =AA30*AB29 -> 55848128
A30: TRX0063 | B30: 45425 | C30: CUST030 | D30: Helen Roberts | E30: P005 | F30: Blender | G30: Appliances | H30: 2 | I30: 59.99 | J30: Debit Card | K30: Central | L30: Standard | M30: 45214 | N30: 119.98 | O30: 0 | P30: =IF(A30<>"", IF(P30="", NOW(), P30), "") -> 46105.94 | Q30: =SUMIFS(N:N, C:C, C30) -> 6459.79 | R30: =COUNTIF($F:$F,F30) -> 29 | S30: =LEFT(D30,1) & MID(D30,FIND(" ",D30)+1,1) -> HR | V30: . | W30: Quantity | X30: Unit_price | Y30: Total_amount | AA30: 753 | AB30: 74168 | AC30: 5584128
A31: TRX0241 | B31: 45427 | C31: CUST029 | D31: Edward Mitchell | E31: P005 | F31: Blender | G31: Appliances | H31: 4 | I31: 59.99 | J31: Debit Card | K31: East | L31: Standard | M31: 44867 | N31: 239.96 | O31: 1 | P31: =IF(A31<>"", IF(P31="", NOW(), P31), "") -> 46105.94 | Q31: =SUMIFS(N:N, C:C, C31) -> 11919.77 | R31: =COUNTIF($F:$F,F31) -> 29 | S31: =LEFT(D31,1) & MID(D31,FIND(" ",D31)+1,1) -> EM | W31: 3 | X31: 250 | Y31: 700 | AA31: 753
A32: TRX0029 | B32: 45427 | C32: CUST017 | D32: Charles Allen | E32: P006 | F32: Office Chair | G32: Furniture | H32: 5 | I32: 199.99 | J32: Cash | K32: South | L32: Standard | M32: 44412 | N32: 999.95 | O32: 2 | P32: =IF(A32<>"", IF(P32="", NOW(), P32), "") -> 46105.94 | Q32: =SUMIFS(N:N, C:C, C32) -> 5089.73 | R32: =COUNTIF($F:$F,F32) -> 15 | S32: =LEFT(D32,1) & MID(D32,FIND(" ",D32)+1,1) -> CA | V32: Goal Seek | W32: =H2 -> 3 | X32: 256.66667 | Y32: =W32*X32 -> 770
A33: TRX0194 | B33: 45428 | C33: CUST006 | D33: Lisa Anderson | E33: P008 | F33: Bookshelf | G33: Furniture | H33: 2 | I33: 149.99 | J33: Credit Card | K33: West | L33: Basic | M33: 44823 | N33: 299.98 | O33: 1 | P33: =IF(A33<>"", IF(P33="", NOW(), P33), "") -> 46105.94 | Q33: =SUMIFS(N:N, C:C, C33) -> 2039.8 | R33: =COUNTIF($F:$F,F33) -> 35 | S33: =LEFT(D33,1) & MID(D33,FIND(" ",D33)+1,1) -> LA
A34: TRX0130 | B34: 45430 | C34: CUST002 | D34: Emma Wilson | E34: P008 | F34: Bookshelf | G34: Furniture | H34: 3 | I34: 149.99 | J34: Credit Card | K34: West | L34: Premium | M34: 45068 | N34: 449.97 | O34: 0 | P34: =IF(A34<>"", IF(P34="", NOW(), P34), "") -> 46105.94 | Q34: =SUMIFS(N:N, C:C, C34) -> 1229.88 | R34: =COUNTIF($F:$F,F34) -> 35 | S34: =LEFT(D34,1) & MID(D34,FIND(" ",D34)+1,1) -> EW
A35: TRX0041 | B35: 45432 | C35: CUST021 | D35: Kevin Scott | E35: P001 | F35: Laptop | G35: Electronics | H35: 1 | I35: 899.99 | J35: Credit Card | K35: West | L35: Premium | M35: 44578 | N35: 899.99 | O35: 2 | P35: =IF(A35<>"", IF(P35="", NOW(), P35), "") -> 46105.94 | Q35: =SUMIFS(N:N, C:C, C35) -> 3259.87 | R35: =COUNTIF($F:$F,F35) -> 24 | S35: =LEFT(D35,1) & MID(D35,FIND(" ",D35)+1,1) -> KS | V35: 6.Most Frequently Purchased Product
A36: TRX0232 | B36: 45434 | C36: CUST012 | D36: Patricia Moore | E36: P007 | F36: Desk | G36: Furniture | H36: 3 | I36: 299.99 | J36: Credit Card | K36: East | L36: Basic | M36: 44824 | N36: 899.97 | O36: 1 | P36: =IF(A36<>"", IF(P36="", NOW(), P36), "") -> 46105.94 | Q36: =SUMIFS(N:N, C:C, C36) -> 9799.73 | R36: =COUNTIF($F:$F,F36) -> 26 | S36: =LEFT(D36,1) & MID(D36,FIND(" ",D36)+1,1) -> PM | V36: Fequently | W36: Product
A37: TRX0021 | B37: 45435 | C37: CUST006 | D37: Lisa Anderson | E37: P004 | F37: Coffee Maker | G37: Appliances | H37: 3 | I37: 79.99 | J37: Cash | K37: South | L37: Basic | M37: 45046 | N37: 239.97 | O37: 1 | P37: =IF(A37<>"", IF(P37="", NOW(), P37), "") -> 46105.94 | Q37: =SUMIFS(N:N, C:C, C37) -> 2039.8 | R37: =COUNTIF($F:$F,F37) -> 14 | S37: =LEFT(D37,1) & MID(D37,FIND(" ",D37)+1,1) -> LA | V37: 35 | W37: =INDEX(F2:F251:R251,MATCH(V37,R2:R251,0),1) -> Bookshelf
A38: TRX0245 | B38: 45438 | C38: CUST031 | D38: Steven Turner | E38: P006 | F38: Office Chair | G38: Furniture | H38: 3 | I38: 199.99 | J38: Credit Card | K38: North | L38: Premium | M38: 45292 | N38: 599.97 | O38: 0 | P38: =IF(A38<>"", IF(P38="", NOW(), P38), "") -> 46105.94 | Q38: =SUMIFS(N:N, C:C, C38) -> 2649.83 | R38: =COUNTIF($F:$F,F38) -> 15 | S38: =LEFT(D38,1) & MID(D38,FIND(" ",D38)+1,1) -> ST | V38: 34 | W38: =INDEX(F3:F252:R252,MATCH(V38,R3:R252,0),1) -> Keyboard
A39: TRX0015 | B39: 45440 | C39: CUST008 | D39: Jennifer Taylor | E39: P002 | F39: Smartphone | G39: Electronics | H39: 5 | I39: 699.99 | J39: PayPal | K39: West | L39: Standard | M39: 44407 | N39: 3499.95 | O39: 2 | P39: =IF(A39<>"", IF(P39="", NOW(), P39), "") -> 46105.94 | Q39: =SUMIFS(N:N, C:C, C39) -> 4739.85 | R39: =COUNTIF($F:$F,F39) -> 31 | S39: =LEFT(D39,1) & MID(D39,FIND(" ",D39)+1,1) -> JT | V39: 31 | W39: =INDEX(F4:F253:R253,MATCH(V39,R4:R253,0),1) -> Smartphone
A40: TRX0202 | B40: 45441 | C40: CUST035 | D40: Harry Morgan | E40: P010 | F40: Keyboard | G40: Electronics | H40: 3 | I40: 89.99 | J40: PayPal | K40: Central | L40: Premium | M40: 45120 | N40: 269.97 | O40: 0 | P40: =IF(A40<>"", IF(P40="", NOW(), P40), "") -> 46105.94 | Q40: =SUMIFS(N:N, C:C, C40) -> 5519.89 | R40: =COUNTIF($F:$F,F40) -> 34 | S40: =LEFT(D40,1) & MID(D40,FIND(" ",D40)+1,1) -> HM | V40: 29 | W40: =INDEX(F5:F254:R254,MATCH(V40,R5:R254,0),1) -> Blender
A41: TRX0042 | B41: 45443 | C41: CUST019 | D41: Daniel King | E41: P004 | F41: Coffee Maker | G41: Appliances | H41: 1 | I41: 79.99 | J41: Cash | K41: North | L41: Standard | M41: 44917 | N41: 79.99 | O41: 1 | P41: =IF(A41<>"", IF(P41="", NOW(), P41), "") -> 46105.94 | Q41: =SUMIFS(N:N, C:C, C41) -> 7309.8 | R41: =COUNTIF($F:$F,F41) -> 14 | S41: =LEFT(D41,1) & MID(D41,FIND(" ",D41)+1,1) -> DK | V41: 26 | W41: =INDEX(F6:F255:R255,MATCH(V41,R6:R255,0),1) -> Monitor
A42: TRX0128 | B42: 45444 | C42: CUST040 | D42: Sharon Butler | E42: P005 | F42: Blender | G42: Appliances | H42: 2 | I42: 59.99 | J42: Cash | K42: West | L42: Basic | M42: 45390 | N42: 119.98 | O42: 0 | P42: =IF(A42<>"", IF(P42="", NOW(), P42), "") -> 46105.94 | Q42: =SUMIFS(N:N, C:C, C42) -> 5619.87 | R42: =COUNTIF($F:$F,F42) -> 29 | S42: =LEFT(D42,1) & MID(D42,FIND(" ",D42)+1,1) -> SB | V42: 24 | W42: =INDEX(F7:F256:R256,MATCH(V42,R7:R256,0),1) -> Laptop
A43: TRX0117 | B43: 45444 | C43: CUST017 | D43: Charles Allen | E43: P010 | F43: Keyboard | G43: Electronics | H43: 1 | I43: 89.99 | J43: Cash | K43: North | L43: Basic | M43: 45141 | N43: 89.99 | O43: 0 | P43: =IF(A43<>"", IF(P43="", NOW(), P43), "") -> 46105.94 | Q43: =SUMIFS(N:N, C:C, C43) -> 5089.73 | R43: =COUNTIF($F:$F,F43) -> 34 | S43: =LEFT(D43,1) & MID(D43,FIND(" ",D43)+1,1) -> CA | V43: 16 | W43: =INDEX(F8:F257:R257,MATCH(V43,R8:R257,0),1) -> Headphones
A44: TRX0208 | B44: 45446 | C44: CUST004 | D44: Sarah Davis | E44: P010 | F44: Keyboard | G44: Electronics | H44: 5 | I44: 89.99 | J44: Credit Card | K44: East | L44: Standard | M44: 44587 | N44: 449.95 | O44: 2 | P44: =IF(A44<>"", IF(P44="", NOW(), P44), "") -> 46105.94 | Q44: =SUMIFS(N:N, C:C, C44) -> 5499.81 | R44: =COUNTIF($F:$F,F44) -> 34 | S44: =LEFT(D44,1) & MID(D44,FIND(" ",D44)+1,1) -> SD | V44: 15 | W44: =INDEX(F9:F258:R258,MATCH(V44,R9:R258,0),1) -> Office Chair
A45: TRX0234 | B45: 45449 | C45: CUST013 | D45: Joseph Jackson | E45: P009 | F45: Monitor | G45: Electronics | H45: 5 | I45: 249.99 | J45: Credit Card | K45: East | L45: Standard | M45: 44707 | N45: 1249.95 | O45: 2 | P45: =IF(A45<>"", IF(P45="", NOW(), P45), "") -> 46105.94 | Q45: =SUMIFS(N:N, C:C, C45) -> 6949.84 | R45: =COUNTIF($F:$F,F45) -> 26 | S45: =LEFT(D45,1) & MID(D45,FIND(" ",D45)+1,1) -> JJ | V45: 14 | W45: =INDEX(F10:F259:R259,MATCH(V45,R10:R259,0),1) -> Coffee Maker
A46: TRX0121 | B46: 45449 | C46: CUST028 | D46: Betty Campbell | E46: P010 | F46: Keyboard | G46: Electronics | H46: 1 | I46: 89.99 | J46: Credit Card | K46: South | L46: Standard | M46: 44582 | N46: 89.99 | O46: 2 | P46: =IF(A46<>"", IF(P46="", NOW(), P46), "") -> 46105.94 | Q46: =SUMIFS(N:N, C:C, C46) -> 5649.84 | R46: =COUNTIF($F:$F,F46) -> 34 | S46: =LEFT(D46,1) & MID(D46,FIND(" ",D46)+1,1) -> BC
A47: TRX0220 | B47: 45450 | C47: CUST003 | D47: Michael Brown | E47: P008 | F47: Bookshelf | G47: Furniture | H47: 2 | I47: 149.99 | J47: Cash | K47: East | L47: Premium | M47: 44645 | N47: 299.98 | O47: 2 | P47: =IF(A47<>"", IF(P47="", NOW(), P47), "") -> 46105.94 | Q47: =SUMIFS(N:N, C:C, C47) -> 6169.74 | R47: =COUNTIF($F:$F,F47) -> 35 | S47: =LEFT(D47,1) & MID(D47,FIND(" ",D47)+1,1) -> MB
A48: TRX0093 | B48: 45452 | C48: CUST050 | D48: Julie Foster | E48: P005 | F48: Blender | G48: Appliances | H48: 4 | I48: 59.99 | J48: Cash | K48: East | L48: Standard | M48: 44435 | N48: 239.96 | O48: 2 | P48: =IF(A48<>"", IF(P48="", NOW(), P48), "") -> 46105.94 | Q48: =SUMIFS(N:N, C:C, C48) -> 239.96 | R48: =COUNTIF($F:$F,F48) -> 29 | S48: =LEFT(D48,1) & MID(D48,FIND(" ",D48)+1,1) -> JF | V48: 7.Compare two lists and extract matching names in a new column
A49: TRX0088 | B49: 45456 | C49: CUST006 | D49: Lisa Anderson | E49: P010 | F49: Keyboard | G49: Electronics | H49: 5 | I49: 89.99 | J49: Cash | K49: Central | L49: Premium | M49: 44579 | N49: 449.95 | O49: 2 | P49: =IF(A49<>"", IF(P49="", NOW(), P49), "") -> 46105.94 | Q49: =SUMIFS(N:N, C:C, C49) -> 2039.8 | R49: =COUNTIF($F:$F,F49) -> 34 | S49: =LEFT(D49,1) & MID(D49,FIND(" ",D49)+1,1) -> LA | V49: Rahul | W49: Amit | X49: =IF(ISNUMBER(MATCH(V49,$W$49:$W$58,0)),"Match","Not Match") -> Not Match
A50: TRX0115 | B50: 45459 | C50: CUST012 | D50: Patricia Moore | E50: P010 | F50: Keyboard | G50: Electronics | H50: 2 | I50: 89.99 | J50: Credit Card | K50: South | L50: Premium | M50: 44471 | N50: 179.98 | O50: 2 | P50: =IF(A50<>"", IF(P50="", NOW(), P50), "") -> 46105.94 | Q50: =SUMIFS(N:N, C:C, C50) -> 9799.73 | R50: =COUNTIF($F:$F,F50) -> 34 | S50: =LEFT(D50,1) & MID(D50,FIND(" ",D50)+1,1) -> PM | V50: Amit | W50: Neha | X50: =IF(ISNUMBER(MATCH(V50,$W$49:$W$58,0)),"Match","Not Match") -> Match
A51: TRX0154 | B51: 45459 | C51: CUST023 | D51: Paul Baker | E51: P001 | F51: Laptop | G51: Electronics | H51: 5 | I51: 899.99 | J51: Credit Card | K51: South | L51: Standard | M51: 44974 | N51: 4499.95 | O51: 1 | P51: =IF(A51<>"", IF(P51="", NOW(), P51), "") -> 46105.94 | Q51: =SUMIFS(N:N, C:C, C51) -> 8309.74 | R51: =COUNTIF($F:$F,F51) -> 24 | S51: =LEFT(D51,1) & MID(D51,FIND(" ",D51)+1,1) -> PB | V51: Neha | W51: Rohit | X51: =IF(ISNUMBER(MATCH(V51,$W$49:$W$58,0)),"Match","Not Match") -> Match
A52: TRX0044 | B52: 45459 | C52: CUST029 | D52: Edward Mitchell | E52: P001 | F52: Laptop | G52: Electronics | H52: 5 | I52: 899.99 | J52: PayPal | K52: East | L52: Premium | M52: 45278 | N52: 4499.95 | O52: 0 | P52: =IF(A52<>"", IF(P52="", NOW(), P52), "") -> 46105.94 | Q52: =SUMIFS(N:N, C:C, C52) -> 11919.77 | R52: =COUNTIF($F:$F,F52) -> 24 | S52: =LEFT(D52,1) & MID(D52,FIND(" ",D52)+1,1) -> EM | V52: Priya | W52: Simran | X52: =IF(ISNUMBER(MATCH(V52,$W$49:$W$58,0)),"Match","Not Match") -> Not Match
A53: TRX0061 | B53: 45460 | C53: CUST028 | D53: Betty Campbell | E53: P005 | F53: Blender | G53: Appliances | H53: 1 | I53: 59.99 | J53: Debit Card | K53: West | L53: Premium | M53: 45190 | N53: 59.99 | O53: 0 | P53: =IF(A53<>"", IF(P53="", NOW(), P53), "") -> 46105.94 | Q53: =SUMIFS(N:N, C:C, C53) -> 5649.84 | R53: =COUNTIF($F:$F,F53) -> 29 | S53: =LEFT(D53,1) & MID(D53,FIND(" ",D53)+1,1) -> BC | V53: Karan | W53: Karan | X53: =IF(ISNUMBER(MATCH(V53,$W$49:$W$58,0)),"Match","Not Match") -> Match
A54: TRX0150 | B54: 45460 | C54: CUST008 | D54: Jennifer Taylor | E54: P007 | F54: Desk | G54: Furniture | H54: 2 | I54: 299.99 | J54: Debit Card | K54: East | L54: Standard | M54: 45253 | N54: 599.98 | O54: 0 | P54: =IF(A54<>"", IF(P54="", NOW(), P54), "") -> 46105.94 | Q54: =SUMIFS(N:N, C:C, C54) -> 4739.85 | R54: =COUNTIF($F:$F,F54) -> 26 | S54: =LEFT(D54,1) & MID(D54,FIND(" ",D54)+1,1) -> JT | V54: Sneha | W54: Ajay | X54: =IF(ISNUMBER(MATCH(V54,$W$49:$W$58,0)),"Match","Not Match") -> Not Match
A55: TRX0025 | B55: 45468 | C55: CUST049 | D55: Raymond Ross | E55: P010 | F55: Keyboard | G55: Electronics | H55: 4 | I55: 89.99 | J55: Debit Card | K55: South | L55: Basic | M55: 45281 | N55: 359.96 | O55: 0 | P55: =IF(A55<>"", IF(P55="", NOW(), P55), "") -> 46105.94 | Q55: =SUMIFS(N:N, C:C, C55) -> 3669.85 | R55: =COUNTIF($F:$F,F55) -> 34 | S55: =LEFT(D55,1) & MID(D55,FIND(" ",D55)+1,1) -> RR | V55: Rohit | W55: Pooja | X55: =IF(ISNUMBER(MATCH(V55,$W$49:$W$58,0)),"Match","Not Match") -> Match
A56: TRX0078 | B56: 45469 | C56: CUST021 | D56: Kevin Scott | E56: P004 | F56: Coffee Maker | G56: Appliances | H56: 1 | I56: 79.99 | J56: PayPal | K56: Central | L56: Premium | M56: 45352 | N56: 79.99 | O56: 0 | P56: =IF(A56<>"", IF(P56="", NOW(), P56), "") -> 46105.94 | Q56: =SUMIFS(N:N, C:C, C56) -> 3259.87 | R56: =COUNTIF($F:$F,F56) -> 14 | S56: =LEFT(D56,1) & MID(D56,FIND(" ",D56)+1,1) -> KS | V56: Anjali | W56: Meena | X56: =IF(ISNUMBER(MATCH(V56,$W$49:$W$58,0)),"Match","Not Match") -> Not Match
A57: TRX0007 | B57: 45469 | C57: CUST009 | D57: Robert Thomas | E57: P010 | F57: Keyboard | G57: Electronics | H57: 2 | I57: 89.99 | J57: Cash | K57: West | L57: Basic | M57: 44438 | N57: 179.98 | O57: 2 | P57: =IF(A57<>"", IF(P57="", NOW(), P57), "") -> 46105.94 | Q57: =SUMIFS(N:N, C:C, C57) -> 3509.9 | R57: =COUNTIF($F:$F,F57) -> 34 | S57: =LEFT(D57,1) & MID(D57,FIND(" ",D57)+1,1) -> RT | V57: Vikas | W57: Vikas | X57: =IF(ISNUMBER(MATCH(V57,$W$49:$W$58,0)),"Match","Not Match") -> Match
A58: TRX0184 | B58: 45471 | C58: CUST046 | D58: Kathleen Bennett | E58: P002 | F58: Smartphone | G58: Electronics | H58: 3 | I58: 699.99 | J58: Credit Card | K58: East | L58: Premium | M58: 45102 | N58: 2099.97 | O58: 1 | P58: =IF(A58<>"", IF(P58="", NOW(), P58), "") -> 46105.94 | Q58: =SUMIFS(N:N, C:C, C58) -> 4309.81 | R58: =COUNTIF($F:$F,F58) -> 31 | S58: =LEFT(D58,1) & MID(D58,FIND(" ",D58)+1,1) -> KB | V58: Pooja | W58: Arjun | X58: =IF(ISNUMBER(MATCH(V58,$W$49:$W$58,0)),"Match","Not Match") -> Match
A59: TRX0104 | B59: 45471 | C59: CUST012 | D59: Patricia Moore | E59: P001 | F59: Laptop | G59: Electronics | H59: 4 | I59: 899.99 | J59: Credit Card | K59: East | L59: Premium | M59: 44993 | N59: 3599.96 | O59: 1 | P59: =IF(A59<>"", IF(P59="", NOW(), P59), "") -> 46105.94 | Q59: =SUMIFS(N:N, C:C, C59) -> 9799.73 | R59: =COUNTIF($F:$F,F59) -> 24 | S59: =LEFT(D59,1) & MID(D59,FIND(" ",D59)+1,1) -> PM
A60: TRX0127 | B60: 45472 | C60: CUST030 | D60: Helen Roberts | E60: P008 | F60: Bookshelf | G60: Furniture | H60: 1 | I60: 149.99 | J60: PayPal | K60: East | L60: Basic | M60: 44851 | N60: 149.99 | O60: 1 | P60: =IF(A60<>"", IF(P60="", NOW(), P60), "") -> 46105.94 | Q60: =SUMIFS(N:N, C:C, C60) -> 6459.79 | R60: =COUNTIF($F:$F,F60) -> 35 | S60: =LEFT(D60,1) & MID(D60,FIND(" ",D60)+1,1) -> HR
A61: TRX0096 | B61: 45474 | C61: CUST002 | D61: Emma Wilson | E61: P010 | F61: Keyboard | G61: Electronics | H61: 2 | I61: 89.99 | J61: PayPal | K61: Central | L61: Premium | M61: 45275 | N61: 179.98 | O61: 0 | P61: =IF(A61<>"", IF(P61="", NOW(), P61), "") -> 46105.94 | Q61: =SUMIFS(N:N, C:C, C61) -> 1229.88 | R61: =COUNTIF($F:$F,F61) -> 34 | S61: =LEFT(D61,1) & MID(D61,FIND(" ",D61)+1,1) -> EW
A62: TRX0192 | B62: 45475 | C62: CUST017 | D62: Charles Allen | E62: P010 | F62: Keyboard | G62: Electronics | H62: 1 | I62: 89.99 | J62: PayPal | K62: West | L62: Standard | M62: 44802 | N62: 89.99 | O62: 1 | P62: =IF(A62<>"", IF(P62="", NOW(), P62), "") -> 46105.94 | Q62: =SUMIFS(N:N, C:C, C62) -> 5089.73 | R62: =COUNTIF($F:$F,F62) -> 34 | S62: =LEFT(D62,1) & MID(D62,FIND(" ",D62)+1,1) -> CA
A63: TRX0052 | B63: 45476 | C63: CUST022 | D63: Susan Green | E63: P010 | F63: Keyboard | G63: Electronics | H63: 1 | I63: 89.99 | J63: Cash | K63: South | L63: Standard | M63: 44611 | N63: 89.99 | O63: 2 | P63: =IF(A63<>"", IF(P63="", NOW(), P63), "") -> 46105.94 | Q63: =SUMIFS(N:N, C:C, C63) -> 1979.89 | R63: =COUNTIF($F:$F,F63) -> 34 | S63: =LEFT(D63,1) & MID(D63,FIND(" ",D63)+1,1) -> SG
A64: TRX0070 | B64: 45476 | C64: CUST007 | D64: David Martinez | E64: P004 | F64: Coffee Maker | G64: Appliances | H64: 5 | I64: 79.99 | J64: Debit Card | K64: Central | L64: Basic | M64: 44981 | N64: 399.95 | O64: 1 | P64: =IF(A64<>"", IF(P64="", NOW(), P64), "") -> 46105.94 | Q64: =SUMIFS(N:N, C:C, C64) -> 1809.84 | R64: =COUNTIF($F:$F,F64) -> 14 | S64: =LEFT(D64,1) & MID(D64,FIND(" ",D64)+1,1) -> DM
A65: TRX0086 | B65: 45481 | C65: CUST020 | D65: Margaret Wright | E65: P008 | F65: Bookshelf | G65: Furniture | H65: 1 | I65: 149.99 | J65: PayPal | K65: North | L65: Basic | M65: 44421 | N65: 149.99 | O65: 2 | P65: =IF(A65<>"", IF(P65="", NOW(), P65), "") -> 46105.94 | Q65: =SUMIFS(N:N, C:C, C65) -> 2099.88 | R65: =COUNTIF($F:$F,F65) -> 35 | S65: =LEFT(D65,1) & MID(D65,FIND(" ",D65)+1,1) -> MW
A66: TRX0113 | B66: 45481 | C66: CUST003 | D66: Michael Brown | E66: P002 | F66: Smartphone | G66: Electronics | H66: 2 | I66: 699.99 | J66: PayPal | K66: East | L66: Premium | M66: 45389 | N66: 1399.98 | O66: 0 | P66: =IF(A66<>"", IF(P66="", NOW(), P66), "") -> 46105.94 | Q66: =SUMIFS(N:N, C:C, C66) -> 6169.74 | R66: =COUNTIF($F:$F,F66) -> 31 | S66: =LEFT(D66,1) & MID(D66,FIND(" ",D66)+1,1) -> MB
A67: TRX0114 | B67: 45481 | C67: CUST018 | D67: Barbara Young | E67: P010 | F67: Keyboard | G67: Electronics | H67: 5 | I67: 89.99 | J67: Debit Card | K67: North | L67: Premium | M67: 45161 | N67: 449.95 | O67: 0 | P67: =IF(A67<>"", IF(P67="", NOW(), P67), "") -> 46105.94 | Q67: =SUMIFS(N:N, C:C, C67) -> 10649.8 | R67: =COUNTIF($F:$F,F67) -> 34 | S67: =LEFT(D67,1) & MID(D67,FIND(" ",D67)+1,1) -> BY
A68: TRX0136 | B68: 45482 | C68: CUST049 | D68: Raymond Ross | E68: P005 | F68: Blender | G68: Appliances | H68: 4 | I68: 59.99 | J68: Cash | K68: South | L68: Standard | M68: 44509 | N68: 239.96 | O68: 2 | P68: =IF(A68<>"", IF(P68="", NOW(), P68), "") -> 46105.94 | Q68: =SUMIFS(N:N, C:C, C68) -> 3669.85 | R68: =COUNTIF($F:$F,F68) -> 29 | S68: =LEFT(D68,1) & MID(D68,FIND(" ",D68)+1,1) -> RR
A69: TRX0018 | B69: 45484 | C69: CUST013 | D69: Joseph Jackson | E69: P003 | F69: Headphones | G69: Electronics | H69: 1 | I69: 149.99 | J69: Cash | K69: Central | L69: Standard | M69: 44909 | N69: 149.99 | O69: 1 | P69: =IF(A69<>"", IF(P69="", NOW(), P69), "") -> 46105.94 | Q69: =SUMIFS(N:N, C:C, C69) -> 6949.84 | R69: =COUNTIF($F:$F,F69) -> 16 | S69: =LEFT(D69,1) & MID(D69,FIND(" ",D69)+1,1) -> JJ
A70: TRX0141 | B70: 45484 | C70: CUST033 | D70: Frank Torres | E70: P007 | F70: Desk | G70: Furniture | H70: 1 | I70: 299.99 | J70: Credit Card | K70: North | L70: Premium | M70: 44891 | N70: 299.99 | O70: 1 | P70: =IF(A70<>"", IF(P70="", NOW(), P70), "") -> 46105.94 | Q70: =SUMIFS(N:N, C:C, C70) -> 1479.91 | R70: =COUNTIF($F:$F,F70) -> 26 | S70: =LEFT(D70,1) & MID(D70,FIND(" ",D70)+1,1) -> FT
... A251: TRX0064 | B251: 45758 | C251: CUST031 | D251: Steven Turner | E251: P010 | F251: Keyboard | G251: Electronics | H251: 3 | I251: 89.99 | J251: Debit Card | K251: North | L251: Premium | M251: 44878 | N251: 269.97 | O251: 2 | P251: =IF(A251<>"", IF(P251="", NOW(), P251), "") -> 46105.94 | Q251: =SUMIFS(N:N, C:C, C251) -> 2649.83 | R251: =COUNTIF($F:$F,F251) -> 34 | S251: =LEFT(D251,1) & MID(D251,FIND(" ",D251)+1,1) -> ST

Sheet Dashboard

Sheet Linear Regression
A1: SUMMARY OUTPUT
A3: Regression Statistics
A4: Multiple R | B4: 0.45809869
A5: R Square | B5: 0.20985441
A6: Adjusted R Square | B6: 0.20665544
A7: Standard Error | B7: 921.40854
A8: Observations | B8: 249
A10: ANOVA
B11: df | C11: SS | D11: MS | E11: F | F11: Significance F
A12: Regression | B12: 1 | C12: 55694513 | D12: 55694513 | E12: 65.60062 | F12: 2.5391277e-14
A13: Residual | B13: 247 | C13: 2.0970144e+08 | D13: 848993.7
A14: Total | B14: 248 | C14: 2.6539596e+08
B16: Coefficients | C16: Standard Error | D16: t Stat | E16: P-value | F16: Lower 95% | G16: Upper 95% | H16: Lower 95.0% | I16: Upper 95.0%
A17: Intercept | B17: -148.18856 | C17: 143.94399 | D17: -1.0294877 | E17: 0.30425761 | F17: -431.70277 | G17: 135.32564 | H17: -431.70277 | I17: 135.32564
A18: 3 | B18: 353.7886 | C18: 43.680728 | D18: 8.0994209 | E18: 2.5391277e-14 | F18: 267.7544 | G18: 439.82281 | H18: 267.7544 | I18: 439.82281

Sheet Scenario Summary
B2: Scenario Summary
D3: Current Values: | E3: Medium Sales | F3: High Sales | G3: low Sales
E4: Created by Ritu on 26-03-2026 Modified by Ritu on 26-03-2026 | F4: Created by Ritu on 26-03-2026 Modified by Ritu on 26-03-2026 | G4: Created by Ritu on 26-03-2026 Modified by Ritu on 26-03-2026
B5: Changing Cells:
C6: $U$30 | D6: 753 | E6: 753 | F6: 800 | G6: 730
C7: $V$30 | D7: 74168 | E7: 74168 | F7: 80000 | G7: 71000
B8: Result Cells:
C9: $U$31
B10: Notes: Current Values column represents values of changing cells at
B11: time Scenario Summary Report was created. Changing cells for each
B12: scenario are highlighted in gray.

Sheet Top 5 Customers
A1: Customer_Name | B1: Total Revenue per customer | C1: Identify High-Value Customers
A2: Paul Baker | B2: =SUMIFS('Final Project Dataset'!$N$2:$N$251,'Final Project Dataset'!$D$2:$D$251,'Top 5 Customers'!A2) -> 8309.74 | C2: =IF(B2>8000,"High Value","Normal") -> High Value
A3: Joseph Jackson | B3: =SUMIFS('Final Project Dataset'!$N$2:$N$251,'Final Project Dataset'!$D$2:$D$251,'Top 5 Customers'!A3) -> 6949.84 | C3: =IF(B3>8000,"High Value","Normal") -> Normal | D3: RANK | E3: TOP REVENUE | F3: Customer_Name
A4: Kevin Scott | B4: =SUMIFS('Final Project Dataset'!$N$2:$N$251,'Final Project Dataset'!$D$2:$D$251,'Top 5 Customers'!A4) -> 3259.87 | C4: =IF(B4>8000,"High Value","Normal") -> Normal | D4: 1 | E4: =LARGE(B2:B51,1) -> 15659.65 | F4: =INDEX(A2:B51,MATCH(E4,B2:B51,0),1) -> Mark Carter
A5: Kathleen Bennett | B5: =SUMIFS('Final Project Dataset'!$N$2:$N$251,'Final Project Dataset'!$D$2:$D$251,'Top 5 Customers'!A5) -> 4309.81 | C5: =IF(B5>8000,"High Value","Normal") -> Normal | D5: 2 | E5: =LARGE(B3:B52,2) -> 11919.77 | F5: =INDEX(A3:B52,MATCH(E5,B3:B52,0),1) -> Edward Mitchell
A6: Michael Brown | B6: =SUMIFS('Final Project Dataset'!$N$2:$N$251,'Final Project Dataset'!$D$2:$D$251,'Top 5 Customers'!A6) -> 6169.74 | C6: =IF(B6>8000,"High Value","Normal") -> Normal | D6: 3 | E6: =LARGE(B4:B53,3) -> 10649.8 | F6: =INDEX(A4:B53,MATCH(E6,B4:B53,0),1) -> Barbara Young
A7: Dorothy Nelson | B7: =SUMIFS('Final Project Dataset'!$N$2:$N$251,'Final Project Dataset'!$D$2:$D$251,'Top 5 Customers'!A7) -> 8269.79 | C7: =IF(B7>8000,"High Value","Normal") -> High Value | D7: 4 | E7: =LARGE(B5:B54,4) -> 9799.73 | F7: =INDEX(A5:B54,MATCH(E7,B5:B54,0),1) -> Patricia Moore
A8: Charles Allen | B8: =SUMIFS('Final Project Dataset'!$N$2:$N$251,'Final Project Dataset'!$D$2:$D$251,'Top 5 Customers'!A8) -> 5089.73 | C8: =IF(B8>8000,"High Value","Normal") -> Normal | D8: 5 | E8: =LARGE(B6:B55,5) -> 8269.79 | F8: =INDEX(A6:B55,MATCH(E8,B6:B55,0),1) -> Dorothy Nelson
A9: Robert Thomas | B9: =SUMIFS('Final Project Dataset'!$N$2:$N$251,'Final Project Dataset'!$D$2:$D$251,'Top 5 Customers'!A9) -> 3509.9 | C9: =IF(B9>8000,"High Value","Normal") -> Normal
A10: Karen Hill | B10: =SUMIFS('Final Project Dataset'!$N$2:$N$251,'Final Project Dataset'!$D$2:$D$251,'Top 5 Customers'!A10) -> 8009.77 | C10: =IF(B10>8000,"High Value","Normal") -> High Value
A11: Susan Green | B11: =SUMIFS('Final Project Dataset'!$N$2:$N$251,'Final Project Dataset'!$D$2:$D$251,'Top 5 Customers'!A11) -> 1979.89 | C11: =IF(B11>8000,"High Value","Normal") -> Normal
A12: Peter Richardson | B12: =SUMIFS('Final Project Dataset'!$N$2:$N$251,'Final Project Dataset'!$D$2:$D$251,'Top 5 Customers'!A12) -> 5949.85 | C12: =IF(B12>8000,"High Value","Normal") -> Normal
A13: Dennis Gray | B13: =SUMIFS('Final Project Dataset'!$N$2:$N$251,'Final Project Dataset'!$D$2:$D$251,'Top 5 Customers'!A13) -> 479.92 | C13: =IF(B13>8000,"High Value","Normal") -> Normal
A14: Michelle Rogers | B14: =SUMIFS('Final Project Dataset'!$N$2:$N$251,'Final Project Dataset'!$D$2:$D$251,'Top 5 Customers'!A14) -> 4199.94 | C14: =IF(B14>8000,"High Value","Normal") -> Normal
A15: George Adams | B15: =SUMIFS('Final Project Dataset'!$N$2:$N$251,'Final Project Dataset'!$D$2:$D$251,'Top 5 Customers'!A15) -> 3779.93 | C15: =IF(B15>8000,"High Value","Normal") -> Normal
A16: Mark Carter | B16: =SUMIFS('Final Project Dataset'!$N$2:$N$251,'Final Project Dataset'!$D$2:$D$251,'Top 5 Customers'!A16) -> 15659.65 | C16: =IF(B16>8000,"High Value","Normal") -> High Value
A17: Maria Garcia | B17: =SUMIFS('Final Project Dataset'!$N$2:$N$251,'Final Project Dataset'!$D$2:$D$251,'Top 5 Customers'!A17) -> 1909.93 | C17: =IF(B17>8000,"High Value","Normal") -> Normal
A18: Virginia Sanders | B18: =SUMIFS('Final Project Dataset'!$N$2:$N$251,'Final Project Dataset'!$D$2:$D$251,'Top 5 Customers'!A18) -> 4789.79 | C18: =IF(B18>8000,"High Value","Normal") -> Normal
A19: Barbara Young | B19: =SUMIFS('Final Project Dataset'!$N$2:$N$251,'Final Project Dataset'!$D$2:$D$251,'Top 5 Customers'!A19) -> 10649.8 | C19: =IF(B19>8000,"High Value","Normal") -> High Value
A20: Patricia Moore | B20: =SUMIFS('Final Project Dataset'!$N$2:$N$251,'Final Project Dataset'!$D$2:$D$251,'Top 5 Customers'!A20) -> 9799.73 | C20: =IF(B20>8000,"High Value","Normal") -> High Value
... A51: John Smith | B51: =SUMIFS('Final Project Dataset'!$N$2:$N$251,'Final Project Dataset'!$D$2:$D$251,'Top 5 Customers'!A51) -> 599.96 | C51: =IF(B51>8000,"High Value","Normal") -> Normal

Sheet Pivot Table
A3: Row Labels | B3: Sum of Total_Amount
A4: Arthur Edwards | B4: 1559.94
A5: Barbara Young | B5: 10649.8
A6: Betty Campbell | B6: 5649.84
A7: Carol Evans | B7: 1149.93
A8: Charles Allen | B8: 5089.73
A9: Cynthia Price | B9: 3769.83
A10: Daniel King | B10: 7309.8
A11: David Martinez | B11: 1809.84
A12: Dennis Gray | B12: 479.92
A13: Dorothy Nelson | B13: 8269.79
A14: Douglas Watson | B14: 4829.89
A15: Edward Mitchell | B15: 11919.77
... A54: Grand Total | B54: 229192.47

Sheet Line Chart
A3: Row Labels | B3: Sum of Total_Amount
A4: 2024 | B4: 38488.78
A5: Apr | B5: 4949.86
A6: May | B6: 6069.76
A7: Jun | B7: 13719.63
A8: Jul | B8: 5379.79
A9: Aug | B9: 8369.74
A10: 2025 | B10: 32058.98
A11: Jan | B11: 12939.56
A12: Feb | B12: 4929.78
A13: Mar | B13: 11219.7
A14: Apr | B14: 2969.94
A15: Grand Total | B15: 70547.76
B21: =GETPIVOTDATA("Total_Amount",$A$3) -> 70547.76

Sheet Pie Chart
A3: Row Labels | B3: Sum of Total_Amount
A4: Appliances | B4: 3019.56
A5: Electronics | B5: 55628.78
A6: Furniture | B6: 11899.42
A7: Grand Total | B7: 70547.76

Sheet Bar Chart
A3: Row Labels | B3: Sum of Total_Amount
A4: Central | B4: 26098.93
A5: East | B5: 44448.83
A6: Grand Total | B6: 70547.76

Sheet Bar Chart1
A3: Row Labels | B3: Sum of Total_Amount
A4: Blender | B4: 1499.75
A5: Bookshelf | B5: 4499.7
A6: Coffee Maker | B6: 1519.81
A7: Desk | B7: 5399.82
A8: Headphones | B8: 2699.82
A9: Keyboard | B9: 1979.78
A10: Laptop | B10: 29699.67
A11: Monitor | B11: 7249.71
A12: Office Chair | B12: 1999.9
A13: Smartphone | B13: 13999.8
A14: Grand Total | B14: 70547.76

Sheet Dounut Chart
A1: Category | B1: (All)
A3: Row Labels | B3: Sum of Total_Amount
A4: Basic | B4: 17369.39
A5: Premium | B5: 30879.22
A6: Standard | B6: 22299.15
A7: Grand Total | B7: 70547.76

Sheet Total Customers
A3: Count of Customer_ID
A4: 68
